raho.py
raho-0.0.2.dist-info/LICENSE
raho-0.0.2.dist-info/METADATA
raho-0.0.2.dist-info/WHEEL
raho-0.0.2.dist-info/entry_points.txt
raho-0.0.2.dist-info/top_level.txt
raho-0.0.2.dist-info/RECORD
