Metadata-Version: 2.1
Name: raho
Version: 0.0.2
Summary: Simple symmetric encryption built on cryptography
Home-page: https://github.com/abhayagiri/raho
Author: Abhayagiri Dev Monk
Author-email: devmonk@abhayagiri.org
License: UNKNOWN
Keywords: cryptography fernet
Platform: UNKNOWN
Classifier: Development Status :: 4 - Beta
Classifier: Intended Audience :: Developers
Classifier: License :: OSI Approved :: ISC License (ISCL)
Classifier: Programming Language :: Python :: 2
Classifier: Programming Language :: Python :: 2.7
Classifier: Programming Language :: Python :: 3
Classifier: Programming Language :: Python :: 3.5
Classifier: Programming Language :: Python :: 3.6
Classifier: Programming Language :: Python :: 3.7
Requires-Python: >=2.7, !=3.0.*, !=3.1.*, !=3.2.*, !=3.3.*, !=3.4.*
Requires-Dist: cryptography
Provides-Extra: test
Requires-Dist: tox ; extra == 'test'
